{
    "p2kwiet138013951168_btnCheckin_onClick_seq0": {
        "id": "p2kwiet138013951168_btnCheckin_onClick_seq0",
        "type": "ACTION_SEQUENCE",
        "params": [{
            "name": "eventobject",
            "value": "eventobject"
        }],
        "language": "js",
        "actions": [{
            "id": "customcode_onClick_499781380139518907",
            "type": "INVOKE_FUNCTION",
            "sequenceKUID": "addFlight",
            "display": "addFlight",
            "inputparams": []
        }]
    }
}