{
    "p2kwiet138013951177_segHome_onRowClick_seq0": {
        "id": "p2kwiet138013951177_segHome_onRowClick_seq0",
        "type": "ACTION_SEQUENCE",
        "params": [{
            "name": "eventobject",
            "value": "eventobject"
        }, {
            "name": "sectionNumber",
            "value": "sectionNumber"
        }, {
            "name": "rowNumber",
            "value": "rowNumber"
        }],
        "language": "js",
        "actions": [{
            "id": "customcode_onRowClick_592071380139513580",
            "type": "INVOKE_FUNCTION",
            "sequenceKUID": "onHomeRowClick",
            "display": "onHomeRowClick",
            "inputparams": []
        }]
    }
}